yaping/__init__.py
yaping/aioping.py
yaping/cli.py
yaping/host.py
yaping/ping.py
yaping/protocol.py
yaping/socket.py
yaping/tools.py
yaping-0.2.0.dist-info/licenses/LICENSE
yaping-0.2.0.dist-info/METADATA
yaping-0.2.0.dist-info/WHEEL
yaping-0.2.0.dist-info/entry_points.txt
yaping-0.2.0.dist-info/top_level.txt
yaping-0.2.0.dist-info/RECORD
