Metadata-Version: 2.4
Name: yaping
Version: 0.2.0
Summary: ping library
Author-email: Jose Tiago Macara Coutinho <coutinhotiago@gmail.com>
License: GPL-3.0-or-later
Project-URL: Documentation, https://tiagocoutinho.github.io/yaping/
Project-URL: Homepage, https://github.com/tiagocoutinho/yaping
Project-URL: Source, https://github.com/tiagocoutinho/yaping
Classifier: Development Status :: 4 - Beta
Classifier: Intended Audience :: Developers
Classifier: Intended Audience :: System Administrators
Classifier: License :: OSI Approved :: GNU General Public License v3 (GPLv3)
Classifier: Programming Language :: Python :: 3
Classifier: Programming Language :: Python :: 3.9
Classifier: Programming Language :: Python :: 3.10
Classifier: Programming Language :: Python :: 3.11
Classifier: Programming Language :: Python :: 3.12
Requires-Python: >=3.9
License-File: LICENSE
Requires-Dist: aiodns
Provides-Extra: dev
Requires-Dist: build>=0.10.0; extra == "dev"
Requires-Dist: twine>=4.0.2; extra == "dev"
Requires-Dist: pytest>=8; extra == "dev"
Requires-Dist: pytest-cov>=5; extra == "dev"
Provides-Extra: docs
Requires-Dist: mkdocs; extra == "docs"
Requires-Dist: mkdocs-material; extra == "docs"
Requires-Dist: mkdocstrings[python]; extra == "docs"
Requires-Dist: pygments; extra == "docs"
Requires-Dist: pymdown-extensions; extra == "docs"
Dynamic: license-file
